simple_system/__init__.py
simple_system/main.py
simple_system_ot_bank/__init__.py
simple_system_ot_bank/main.py
simple_system_ot_bank-0.0.1.dist-info/METADATA
simple_system_ot_bank-0.0.1.dist-info/WHEEL
simple_system_ot_bank-0.0.1.dist-info/top_level.txt
simple_system_ot_bank-0.0.1.dist-info/RECORD
