Metadata-Version: 2.2
Name: simple_system_ot_bank
Version: 0.0.1
Summary: Simple Banking System
Home-page: https://github.com/kurokagami/python-optimize-fundamentals
Author: KuroKagami
Author-email: jeangabriel0990@gmail.com
Requires-Python: >=3.12
Requires-Dist: tzlocal
Dynamic: author
Dynamic: author-email
Dynamic: description
Dynamic: description-content-type
Dynamic: home-page
Dynamic: requires-dist
Dynamic: requires-python
Dynamic: summary
